<?xml version="1.0" encoding="UTF-8"?>
<Organisme id="gendarmerie-57683-01" codeInsee="57683" dateMiseAJour="2019-01-22"
           pivotLocal="gendarmerie"
           idPresta="1011511">
   <Nom>Brigade de gendarmerie - Uckange</Nom>
   <EditeurSource>La Direction de l'information légale et administrative (Premier ministre)</EditeurSource>
   <Adresse type="géopostale">
      <Ligne>14 Rue Jean Moulin</Ligne>
      <CodePostal>57270</CodePostal>
      <NomCommune>Uckange</NomCommune>
      <Localisation>
         <Latitude>49.30388285</Latitude>
         <Longitude>6.14308577</Longitude>
         <Précision>8</Précision>
      </Localisation>
   </Adresse>
   <CoordonnéesNum>
      <Téléphone>03 82 86 17 17</Téléphone>
      <Email>https://www.contacterlagendarmerie.fr</Email>
      <Url>http://www.gendarmerie.interieur.gouv.fr</Url>
   </CoordonnéesNum>
</Organisme>