<?xml version="1.0" encoding="UTF-8"?>
<Organisme id="mairie-61046-01" codeInsee="61046" dateMiseAJour="2021-02-08"
           pivotLocal="mairie">
   <Nom>Mairie - Bizou</Nom>
   <EditeurSource>La Direction de l'information légale et administrative (Premier ministre)</EditeurSource>
   <Adresse type="géopostale">
      <Ligne>2 rue Saint-Blaise</Ligne>
      <CodePostal>61290</CodePostal>
      <NomCommune>Bizou</NomCommune>
      <Localisation>
         <Latitude>48.4367980957</Latitude>
         <Longitude>0.780704021454</Longitude>
         <Précision>6</Précision>
      </Localisation>
      <Accessibilité type="ACC"/>
   </Adresse>
   <CoordonnéesNum>
      <Téléphone>02 33 73 61 62</Téléphone>
      <Email>mairie.de.bizou@wanadoo.fr</Email>
   </CoordonnéesNum>
   <Ouverture>
      <PlageJ début="jeudi" fin="jeudi">
         <PlageH début="09:30:00" fin="12:30:00"/>
      </PlageJ>
      <PlageJ début="lundi" fin="lundi">
         <PlageH début="09:30:00" fin="12:00:00"/>
      </PlageJ>
   </Ouverture>
</Organisme>