<?xml version="1.0" encoding="UTF-8"?>
<Organisme id="gendarmerie-29274-01" codeInsee="29274" dateMiseAJour="2019-01-22"
           pivotLocal="gendarmerie"
           idPresta="1006372">
   <Nom>Brigade de gendarmerie - Scaër</Nom>
   <EditeurSource>La Direction de l'information légale et administrative (Premier ministre)</EditeurSource>
   <Adresse type="géopostale">
      <Ligne>17 Rue Henri Croissant</Ligne>
      <CodePostal>29390</CodePostal>
      <NomCommune>Scaër</NomCommune>
      <Localisation>
         <Latitude>48.02317915</Latitude>
         <Longitude>-3.71775102</Longitude>
         <Précision>8</Précision>
      </Localisation>
   </Adresse>
   <CoordonnéesNum>
      <Téléphone>02 98 59 42 02</Téléphone>
      <Email>https://www.contacterlagendarmerie.fr</Email>
      <Url>http://www.gendarmerie.interieur.gouv.fr</Url>
   </CoordonnéesNum>
</Organisme>