<?xml version="1.0" encoding="UTF-8"?>
<Organisme codeInsee="83012" dateMiseAJour="2021-09-02" id="permanence_juridique-83012-01" idPresta="612f2edbb473e40555def554" pivotLocal="permanence_juridique">
    <Nom>Point-justice - relais d'accès au droit  Maison des services au public de Barjols</Nom>
    <EditeurSource>Ministère de la Justice</EditeurSource>
    <Adresse type="géopostale">
        <Ligne>avenue de Garessio</Ligne>
        <CodePostal>83670</CodePostal>
        <NomCommune>BARJOLS</NomCommune>
        <Localisation>
            <Latitude>43.56515</Latitude>
            <Longitude>6.005176</Longitude>
            <Précision>6.0</Précision>
        </Localisation>
    </Adresse>
    <CoordonnéesNum>
        <Téléphone>04 94 77 10 08</Téléphone>
        <Télécopie>04 79 34 01 95</Télécopie>
    </CoordonnéesNum>
</Organisme>