<?xml version="1.0" encoding="UTF-8"?>
<Organisme id="huissiers_justice-44109-02" codeInsee="44109" dateMiseAJour="2021-09-27"
           pivotLocal="huissiers_justice">
   <Nom>Chambre départementale des huissiers de justice - Loire-Atlantique</Nom>
   <EditeurSource>La Direction de l'information légale et administrative (Premier ministre)</EditeurSource>
   <Adresse type="géopostale">
      <Ligne>20 boulevard Emile Romanet</Ligne>
      <Ligne>BP 88750</Ligne>
      <Ligne>Christophe Leblanc</Ligne>
      <CodePostal>44187</CodePostal>
      <NomCommune>Nantes Cedex 4</NomCommune>
      <Localisation>
         <Latitude>47.210748</Latitude>
         <Longitude>-1.607178</Longitude>
         <Précision>8</Précision>
      </Localisation>
   </Adresse>
   <CoordonnéesNum>
      <Email>scp-proyart-leblanc@wanadoo.fr</Email>
      <Url>https://www.huissier-justice.fr/</Url>
   </CoordonnéesNum>
</Organisme>