<?xml version="1.0" encoding="UTF-8"?>
<Organisme id="mairie-32229-01" codeInsee="32229" dateMiseAJour="2020-10-08"
           pivotLocal="mairie">
   <Nom>Mairie - Mansempuy</Nom>
   <EditeurSource>La Direction de l'information légale et administrative (Premier ministre)</EditeurSource>
   <Adresse type="géopostale">
      <Ligne>Le Village</Ligne>
      <CodePostal>32120</CodePostal>
      <NomCommune>Mansempuy</NomCommune>
      <Localisation>
         <Latitude>43.739546</Latitude>
         <Longitude>0.81263</Longitude>
         <Précision>8</Précision>
      </Localisation>
      <Accessibilité type="ACC"/>
   </Adresse>
   <CoordonnéesNum>
      <Téléphone>05 62 06 79 62</Téléphone>
      <Télécopie>05 62 06 79 62</Télécopie>
      <Email>mairie.mansempuy@orange.fr</Email>
   </CoordonnéesNum>
   <Ouverture>
      <PlageJ début="lundi" fin="lundi">
         <PlageH début="14:00:00" fin="18:00:00"/>
      </PlageJ>
   </Ouverture>
</Organisme>