<?xml version="1.0" encoding="UTF-8"?>
<Organisme id="gendarmerie-62063-01" codeInsee="62063" dateMiseAJour="2019-01-22"
           pivotLocal="gendarmerie"
           idPresta="1013681">
   <Nom>Brigade de gendarmerie - Avesnes-le-Comte</Nom>
   <EditeurSource>La Direction de l'information légale et administrative (Premier ministre)</EditeurSource>
   <Adresse type="géopostale">
      <Ligne>25 Rue des Fosses</Ligne>
      <CodePostal>62810</CodePostal>
      <NomCommune>Avesnes-le-Comte</NomCommune>
      <Localisation>
         <Latitude>50.27589127</Latitude>
         <Longitude>2.53005535</Longitude>
         <Précision>8</Précision>
      </Localisation>
   </Adresse>
   <CoordonnéesNum>
      <Téléphone>03 21 48 40 17</Téléphone>
      <Email>https://www.contacterlagendarmerie.fr</Email>
      <Url>http://www.gendarmerie.interieur.gouv.fr</Url>
   </CoordonnéesNum>
</Organisme>