<?xml version="1.0" encoding="UTF-8"?>
<Organisme id="mairie-34040-01" codeInsee="34040" dateMiseAJour="2021-07-07"
           pivotLocal="mairie">
   <Nom>Mairie - Brenas</Nom>
   <EditeurSource>La Direction de l'information légale et administrative (Premier ministre)</EditeurSource>
   <Adresse type="géopostale">
      <Ligne>Le Village</Ligne>
      <CodePostal>34650</CodePostal>
      <NomCommune>Brenas</NomCommune>
      <Localisation>
         <Latitude>43.6531295776</Latitude>
         <Longitude>3.25650405884</Longitude>
         <Précision>4</Précision>
      </Localisation>
      <Accessibilité type="ACC"/>
   </Adresse>
   <CoordonnéesNum>
      <Téléphone>04 67 23 29 77</Téléphone>
      <Email>mairie-brenas@orange.fr</Email>
   </CoordonnéesNum>
   <Ouverture>
      <PlageJ début="jeudi" fin="jeudi">
         <PlageH début="09:30:00" fin="12:00:00"/>
         <PlageH début="14:30:00" fin="18:00:00"/>
      </PlageJ>
   </Ouverture>
</Organisme>