<?xml version="1.0" encoding="UTF-8"?>
<Organisme id="onac-34172-01" codeInsee="34172" dateMiseAJour="2021-12-06"
           pivotLocal="onac">
   <Nom>Office national des anciens combattants et victimes de guerre (ONACVG) - Service départemental - Hérault</Nom>
   <EditeurSource>La Direction de l'information légale et administrative (Premier ministre)</EditeurSource>
   <Adresse type="géopostale">
      <Ligne>CS 79551</Ligne>
      <Ligne>311 avenue Masséna</Ligne>
      <CodePostal>34961</CodePostal>
      <NomCommune>Montpellier Cedex 2</NomCommune>
      <Localisation>
         <Latitude>43.610906</Latitude>
         <Longitude>3.845969</Longitude>
         <Précision>8</Précision>
      </Localisation>
      <Accessibilité type="ACC"/>
   </Adresse>
   <CoordonnéesNum>
      <Téléphone>04 67 16 59 30</Téléphone>
      <Email>https://www.onac-vg.fr/contact</Email>
      <Url>https://www.onac-vg.fr</Url>
   </CoordonnéesNum>
   <Ouverture>
      <PlageJ début="lundi" fin="vendredi">
         <PlageH début="09:00:00" fin="12:00:00"/>
      </PlageJ>
   </Ouverture>
   <Commentaire>Uniquement sur rendez-vous du lundi au jeudi de 9h à 12h et sans rendez-vous le vendredi de 9h à 12h</Commentaire>
</Organisme>