<?xml version="1.0" encoding="UTF-8"?>
<Organisme id="chambre_metier-65440-01" codeInsee="65440" dateMiseAJour="2021-06-07"
           pivotLocal="chambre_metier">
   <Nom>Chambre de métiers et de l'artisanat (CMA) - Hautes-Pyrénées</Nom>
   <EditeurSource>La Direction de l'information légale et administrative (Premier ministre)</EditeurSource>
   <Adresse type="géopostale">
      <Ligne>10 bis rue du 4-Septembre</Ligne>
      <Ligne>BP 336</Ligne>
      <CodePostal>65003</CodePostal>
      <NomCommune>Tarbes Cedex</NomCommune>
      <Localisation>
         <Latitude>43.2290000916</Latitude>
         <Longitude>0.0800940021873</Longitude>
         <Précision>8</Précision>
      </Localisation>
      <Accessibilité type="ACC"/>
   </Adresse>
   <CoordonnéesNum>
      <Téléphone>05 62 56 60 60</Téléphone>
      <Télécopie>05 62 34 62 61</Télécopie>
      <Email>contact@cma65.fr</Email>
      <Url>http://www.cma65.fr</Url>
   </CoordonnéesNum>
   <Ouverture>
      <PlageJ début="lundi" fin="vendredi">
         <PlageH début="08:30:00" fin="12:00:00"/>
         <PlageH début="13:30:00" fin="17:00:00"/>
      </PlageJ>
   </Ouverture>
</Organisme>