<?xml version="1.0" encoding="UTF-8"?>
<Organisme id="mairie-63110-01" codeInsee="63110" dateMiseAJour="2021-06-07"
           pivotLocal="mairie">
   <Nom>Mairie - Cisternes-la-Forêt</Nom>
   <EditeurSource>La Direction de l'information légale et administrative (Premier ministre)</EditeurSource>
   <Adresse type="géopostale">
      <Ligne>Le Bourg</Ligne>
      <CodePostal>63740</CodePostal>
      <NomCommune>Cisternes-la-Forêt</NomCommune>
      <Localisation>
         <Latitude>45.7900009155</Latitude>
         <Longitude>2.70603990555</Longitude>
         <Précision>8</Précision>
      </Localisation>
      <Accessibilité type="ACC"/>
   </Adresse>
   <CoordonnéesNum>
      <Téléphone>04 73 87 81 05</Téléphone>
      <Télécopie>04 73 87 81 05</Télécopie>
      <Email>mairie-cisternes@wanadoo.fr</Email>
   </CoordonnéesNum>
   <Ouverture>
      <PlageJ début="jeudi" fin="jeudi">
         <PlageH début="14:00:00" fin="17:00:00"/>
      </PlageJ>
      <PlageJ début="vendredi" fin="vendredi">
         <PlageH début="09:00:00" fin="12:00:00"/>
      </PlageJ>
      <PlageJ début="lundi" fin="lundi">
         <PlageH début="09:00:00" fin="12:00:00"/>
      </PlageJ>
   </Ouverture>
</Organisme>