<?xml version="1.0" encoding="UTF-8"?>
<Organisme id="sous_pref-63178-01" codeInsee="63178" dateMiseAJour="2021-02-18"
           pivotLocal="sous_pref">
   <Nom>Sous-préfecture - Issoire</Nom>
   <EditeurSource>La Direction de l'information légale et administrative (Premier ministre)</EditeurSource>
   <Adresse type="géopostale">
      <Ligne>Boulevard de la Sous-Préfecture</Ligne>
      <CodePostal>63501</CodePostal>
      <NomCommune>Issoire Cedex</NomCommune>
      <Localisation>
         <Latitude>45.5417938232</Latitude>
         <Longitude>3.24817204475</Longitude>
         <Précision>6</Précision>
      </Localisation>
   </Adresse>
   <CoordonnéesNum>
      <Téléphone>04 73 89 07 76</Téléphone>
      <Télécopie>+33 4 73 89 29 87</Télécopie>
      <Email>sous-prefecture-de-issoire@puy-de-dome.pref.gouv.fr</Email>
      <Url>http://www.puy-de-dome.gouv.fr</Url>
   </CoordonnéesNum>
   <Ouverture>
      <PlageJ début="lundi" fin="vendredi">
         <PlageH début="08:30:00" fin="12:15:00"/>
         <Note>uniquement sur rendez-vous</Note>
      </PlageJ>
   </Ouverture>
</Organisme>