<?xml version="1.0" encoding="UTF-8"?>
<Organisme id="mairie-54217-01" codeInsee="54217" dateMiseAJour="2021-05-10"
           pivotLocal="mairie">
   <Nom>Mairie - Gélacourt</Nom>
   <EditeurSource>La Direction de l'information légale et administrative (Premier ministre)</EditeurSource>
   <Adresse type="géopostale">
      <Ligne>10 bis Grande rue</Ligne>
      <CodePostal>54120</CodePostal>
      <NomCommune>Gélacourt</NomCommune>
      <Localisation>
         <Latitude>48.517616272</Latitude>
         <Longitude>6.72945976257</Longitude>
         <Précision>8</Précision>
      </Localisation>
      <Accessibilité type="ACC">rampe, ascenseur à la salle des fêtes</Accessibilité>
   </Adresse>
   <CoordonnéesNum>
      <Téléphone>03 83 75 22 42</Téléphone>
      <Email>mairie.gelacourt@wanadoo.fr</Email>
   </CoordonnéesNum>
   <Ouverture>
      <PlageJ début="lundi" fin="lundi">
         <PlageH début="18:00:00" fin="19:00:00"/>
      </PlageJ>
      <PlageJ début="jeudi" fin="jeudi">
         <PlageH début="11:00:00" fin="12:00:00"/>
      </PlageJ>
   </Ouverture>
</Organisme>