<?xml version="1.0" encoding="UTF-8"?>
<Organisme id="mairie-54296-01" codeInsee="54296" dateMiseAJour="2021-05-10"
           pivotLocal="mairie">
   <Nom>Mairie - Laneuvelotte</Nom>
   <EditeurSource>La Direction de l'information légale et administrative (Premier ministre)</EditeurSource>
   <Adresse type="géopostale">
      <Ligne>35 Grande rue</Ligne>
      <CodePostal>54280</CodePostal>
      <NomCommune>Laneuvelotte</NomCommune>
      <Localisation>
         <Latitude>48.6888999939</Latitude>
         <Longitude>6.24878978729</Longitude>
         <Précision>8</Précision>
      </Localisation>
      <Accessibilité type="ACC"/>
   </Adresse>
   <CoordonnéesNum>
      <Téléphone>03 83 20 50 06</Téléphone>
      <Email>accueil@laneuvelotte.fr</Email>
      <Url>http://www.laneuvelotte.fr</Url>
   </CoordonnéesNum>
   <Ouverture>
      <PlageJ début="lundi" fin="lundi">
         <PlageH début="15:00:00" fin="19:00:00"/>
      </PlageJ>
      <PlageJ début="vendredi" fin="vendredi">
         <PlageH début="15:00:00" fin="18:00:00"/>
      </PlageJ>
   </Ouverture>
</Organisme>