<?xml version="1.0" encoding="UTF-8"?>
<Organisme id="gendarmerie-97212-01" codeInsee="97212" dateMiseAJour="2019-01-22"
           pivotLocal="gendarmerie"
           idPresta="1002144">
   <Nom>Brigade de gendarmerie - Gros-Morne</Nom>
   <EditeurSource>La Direction de l'information légale et administrative (Premier ministre)</EditeurSource>
   <Adresse type="géopostale">
      <Ligne>Le bourg</Ligne>
      <CodePostal>97213</CodePostal>
      <NomCommune>Gros-Morne</NomCommune>
      <Localisation>
         <Latitude>14.70962079</Latitude>
         <Longitude>-60.9999591</Longitude>
         <Précision>4</Précision>
      </Localisation>
   </Adresse>
   <CoordonnéesNum>
      <Téléphone>+596 67 80 63</Téléphone>
      <Email>https://www.contacterlagendarmerie.fr</Email>
      <Url>http://www.gendarmerie.interieur.gouv.fr</Url>
   </CoordonnéesNum>
</Organisme>