<?xml version="1.0" encoding="UTF-8"?>
<Organisme id="mairie-36192-01" codeInsee="36192" dateMiseAJour="2021-03-08"
           pivotLocal="mairie">
   <Nom>Mairie - Saint-Gaultier</Nom>
   <EditeurSource>La Direction de l'information légale et administrative (Premier ministre)</EditeurSource>
   <Adresse type="géopostale">
      <Ligne>9 place de l'Hôtel-de-Ville</Ligne>
      <CodePostal>36800</CodePostal>
      <NomCommune>Saint-Gaultier</NomCommune>
      <Localisation>
         <Latitude>46.6350928</Latitude>
         <Longitude>1.4228321</Longitude>
         <Précision>6</Précision>
      </Localisation>
      <Accessibilité type="ACC">les personnes à mobilité réduite sont invitées à accéder à la mairie par l'arrière du bâtiment</Accessibilité>
   </Adresse>
   <CoordonnéesNum>
      <Téléphone>02 54 01 66 00</Téléphone>
      <Télécopie>02 54 01 66 09</Télécopie>
      <Email>st-gaultier.mairie@wanadoo.fr</Email>
   </CoordonnéesNum>
   <Ouverture>
      <PlageJ début="lundi" fin="vendredi">
         <PlageH début="09:00:00" fin="12:15:00"/>
         <PlageH début="14:00:00" fin="17:30:00"/>
      </PlageJ>
      <PlageJ début="samedi" fin="samedi">
         <PlageH début="09:00:00" fin="12:15:00"/>
      </PlageJ>
   </Ouverture>
</Organisme>