<?xml version="1.0" encoding="UTF-8"?>
<Organisme id="gendarmerie-14764-01" codeInsee="14764" dateMiseAJour="2019-01-22"
           pivotLocal="gendarmerie"
           idPresta="1007038">
   <Nom>Brigade de gendarmerie - Pont-d'Ouilly</Nom>
   <EditeurSource>La Direction de l'information légale et administrative (Premier ministre)</EditeurSource>
   <Adresse type="géopostale">
      <Ligne>Rue de la Libération</Ligne>
      <CodePostal>14690</CodePostal>
      <NomCommune>Pont-d'Ouilly</NomCommune>
      <Localisation>
         <Latitude>48.87566012</Latitude>
         <Longitude>-0.41096172</Longitude>
         <Précision>6</Précision>
      </Localisation>
   </Adresse>
   <CoordonnéesNum>
      <Téléphone>02 31 59 17 56</Téléphone>
      <Email>https://www.contacterlagendarmerie.fr</Email>
      <Url>http://www.gendarmerie.interieur.gouv.fr</Url>
   </CoordonnéesNum>
</Organisme>