<?xml version="1.0" encoding="UTF-8"?>
<Organisme id="mairie-14643-01" codeInsee="14643" dateMiseAJour="2021-02-08"
           pivotLocal="mairie">
   <Nom>Mairie - Saint-Paul-du-Vernay</Nom>
   <EditeurSource>La Direction de l'information légale et administrative (Premier ministre)</EditeurSource>
   <Adresse type="géopostale">
      <Ligne>29 rue Éternelle</Ligne>
      <CodePostal>14490</CodePostal>
      <NomCommune>Saint-Paul-du-Vernay</NomCommune>
      <Localisation>
         <Latitude>49.1861086</Latitude>
         <Longitude>-0.7613524</Longitude>
         <Précision>6</Précision>
      </Localisation>
      <Accessibilité type="ACC"/>
   </Adresse>
   <CoordonnéesNum>
      <Téléphone>02 31 21 63 57</Téléphone>
      <Email>stpaulduvernay@wanadoo.fr</Email>
   </CoordonnéesNum>
   <Ouverture>
      <PlageJ début="mardi" fin="mardi">
         <PlageH début="17:00:00" fin="19:00:00"/>
         <Note>Accueil fermé le mardi en juillet-août.</Note>
      </PlageJ>
      <PlageJ début="vendredi" fin="vendredi">
         <PlageH début="17:00:00" fin="19:00:00"/>
      </PlageJ>
   </Ouverture>
</Organisme>