<?xml version="1.0" encoding="UTF-8"?>
<Organisme id="pmi-14488-01" codeInsee="14488" dateMiseAJour="2021-04-12" pivotLocal="pmi">
   <Nom>Centre de protection maternelle et infantile (PMI) - Ouistreham</Nom>
   <EditeurSource>La Direction de l'information légale et administrative (Premier ministre)</EditeurSource>
   <Adresse type="géopostale">
      <Ligne>Route de Lion</Ligne>
      <CodePostal>14150</CodePostal>
      <NomCommune>Ouistreham</NomCommune>
      <Localisation>
         <Latitude>49.2872009277</Latitude>
         <Longitude>-0.269645988941</Longitude>
         <Précision>6</Précision>
      </Localisation>
      <Accessibilité type="ACC"/>
   </Adresse>
   <CoordonnéesNum>
      <Téléphone>02 31 97 16 09</Téléphone>
      <Url>http://www.calvados.fr</Url>
   </CoordonnéesNum>
   <Ouverture>
      <PlageJ début="lundi" fin="vendredi">
         <PlageH début="09:00:00" fin="12:00:00"/>
         <PlageH début="14:00:00" fin="16:30:00"/>
         <Note>Permanence pour la pesée le mardi matin sur rendez-vous.</Note>
      </PlageJ>
   </Ouverture>
</Organisme>