<?xml version="1.0" encoding="UTF-8"?>
<Organisme codeInsee="18033" dateMiseAJour="2021-09-17" id="aav-18033-01" idPresta="51b08cb7b473e41478000b3a" pivotLocal="aav">
    <Nom>relais enfance et famille - Bourges</Nom>
    <EditeurSource>Ministère de la Justice</EditeurSource>
    <Adresse type="géopostale">
        <Ligne>2 rue du Pré Doulet</Ligne>
        <CodePostal>18000</CodePostal>
        <NomCommune>BOURGES</NomCommune>
        <Localisation>
            <Latitude>47.081258</Latitude>
            <Longitude>2.38717</Longitude>
            <Précision>8</Précision>
        </Localisation>
    </Adresse>
    <Adresse type="géopostale">
        <Ligne>2 rue du Pré Doulet</Ligne>
        <CodePostal>18000</CodePostal>
        <NomCommune>BOURGES</NomCommune>
    </Adresse>
    <CoordonnéesNum>
        <Téléphone>02 48 70 02 72</Téléphone>
        <Télécopie>02 48 24 04 66</Télécopie>
        <Email>mailto:relaisenfanceetfamille@wanadoo.fr</Email>
        <Url>http://www.relais-enfance-famille.fr/</Url>
    <Sve>['http://www.justice.gouv.fr/sve']</Sve>
    </CoordonnéesNum>
</Organisme>