<?xml version="1.0" encoding="UTF-8"?>
<Organisme id="mairie-48175-01" codeInsee="48175" dateMiseAJour="2020-07-15"
           pivotLocal="mairie">
   <Nom>Mairie - Saint-Pierre-de-Nogaret</Nom>
   <EditeurSource>La Direction de l'information légale et administrative (Premier ministre)</EditeurSource>
   <Adresse type="géopostale">
      <Ligne>Nogardel</Ligne>
      <CodePostal>48340</CodePostal>
      <NomCommune>Saint-Pierre-de-Nogaret</NomCommune>
      <Localisation>
         <Latitude>44.4622917</Latitude>
         <Longitude>3.1364991</Longitude>
         <Précision>8</Précision>
      </Localisation>
      <Accessibilité type="ACC">rampe</Accessibilité>
   </Adresse>
   <CoordonnéesNum>
      <Téléphone>04 66 32 64 08</Téléphone>
      <Email>mairie.st-pierre-nogaret.48@wanadoo.fr</Email>
   </CoordonnéesNum>
   <Ouverture>
      <PlageJ début="mardi" fin="mardi">
         <PlageH début="13:30:00" fin="17:30:00"/>
      </PlageJ>
      <PlageJ début="jeudi" fin="jeudi">
         <PlageH début="08:30:00" fin="12:00:00"/>
      </PlageJ>
   </Ouverture>
</Organisme>