<?xml version="1.0" encoding="UTF-8"?>
<Organisme codeInsee="30334" dateMiseAJour="2021-12-14" id="ti-30334-01" idPresta="5e159874b473e45834f55259" pivotLocal="ti">
    <Nom>Tribunal de proximité d'Uzès</Nom>
    <EditeurSource>Ministère de la Justice</EditeurSource>
    <Adresse type="géopostale">
        <Ligne>PLACE DE L&#39;EVECHE</Ligne>
        <Ligne>CS 41109</Ligne>
        <CodePostal>30701</CodePostal>
        <NomCommune>UZES CEDEX</NomCommune>
        <Localisation>
            <Latitude>44.012128</Latitude>
            <Longitude>4.421896</Longitude>
            <Précision>6.0</Précision>
        </Localisation>
    </Adresse>
    <Adresse type="géopostale">
        <Ligne>PLACE DE L&#39;EVECHE</Ligne>
        <Ligne>CS 41109</Ligne>
        <CodePostal>30701</CodePostal>
        <NomCommune>UZES CEDEX</NomCommune>
    </Adresse>
    <CoordonnéesNum>
        <Téléphone>04 66 22 12 12</Téléphone>
        <Télécopie>04 66 22 98 20</Télécopie>
        <Email>mailto:tprx-uzes@justice.fr</Email>
    </CoordonnéesNum>
</Organisme>