<?xml version="1.0" encoding="UTF-8"?>
<Organisme codeInsee="50147" dateMiseAJour="2021-09-02" id="aav-50147-01" idPresta="51b08ca3b473e414780006be" pivotLocal="aav">
    <Nom>aide aux victimes, contrôle judiciaire socio-éducatif, médiation pénale (ACJM) - Coutances</Nom>
    <EditeurSource>Ministère de la Justice</EditeurSource>
    <Adresse type="géopostale">
        <Ligne>18 rue de l&#39;Ecluse Chette</Ligne>
        <Ligne>BP 405</Ligne>
        <CodePostal>50204</CodePostal>
        <NomCommune>COUTANCES CEDEX</NomCommune>
        <Localisation>
            <Latitude>49.053058</Latitude>
            <Longitude>-1.444139</Longitude>
            <Précision>8</Précision>
        </Localisation>
    </Adresse>
    <Adresse type="géopostale">
        <Ligne>18 rue de l&#39;Ecluse Chette</Ligne>
        <Ligne>BP 405</Ligne>
        <CodePostal>50204</CodePostal>
        <NomCommune>COUTANCES CEDEX</NomCommune>
    </Adresse>
    <CoordonnéesNum>
        <Téléphone>02 33 19 05 87</Téléphone>
        <Télécopie>02 33 19 05 86</Télécopie>
        <Email>mailto:acjm.siege@wanadoo.fr</Email>
    <Sve>['http://www.justice.gouv.fr/sve']</Sve>
    </CoordonnéesNum>
</Organisme>