<?xml version="1.0" encoding="UTF-8"?>
<Organisme id="mairie-42040-01" codeInsee="42040" dateMiseAJour="2020-12-15"
           pivotLocal="mairie">
   <Nom>Mairie - La Chamba</Nom>
   <EditeurSource>La Direction de l'information légale et administrative (Premier ministre)</EditeurSource>
   <Adresse type="géopostale">
      <Ligne>2 route de l'Alisier</Ligne>
      <CodePostal>42440</CodePostal>
      <NomCommune>La Chamba</NomCommune>
      <Localisation>
         <Latitude>45.755669</Latitude>
         <Longitude>3.757004</Longitude>
         <Précision>8</Précision>
      </Localisation>
      <Accessibilité type="NAC"/>
   </Adresse>
   <CoordonnéesNum>
      <Téléphone>04 77 24 75 92</Téléphone>
      <Email>mairie-lachamba@orange.fr</Email>
   </CoordonnéesNum>
   <Ouverture>
      <PlageJ début="mardi" fin="mardi">
         <PlageH début="14:00:00" fin="18:00:00"/>
      </PlageJ>
      <PlageJ début="jeudi" fin="jeudi">
         <PlageH début="14:00:00" fin="18:00:00"/>
      </PlageJ>
   </Ouverture>
</Organisme>