<?xml version="1.0" encoding="UTF-8"?>
<Organisme id="mairie-02104-01" codeInsee="02104" dateMiseAJour="2016-11-14"
           pivotLocal="mairie">
   <Nom>Mairie - Bouffignereux</Nom>
   <EditeurSource>La Direction de l'information légale et administrative (Premier ministre)</EditeurSource>
   <Adresse type="géopostale">
      <Ligne>Rue de l'Église</Ligne>
      <CodePostal>02160</CodePostal>
      <NomCommune>Bouffignereux</NomCommune>
      <Localisation>
         <Latitude>49.3731002808</Latitude>
         <Longitude>3.84454011917</Longitude>
         <Précision>6</Précision>
      </Localisation>
      <Accessibilité type="ACC"/>
   </Adresse>
   <CoordonnéesNum>
      <Téléphone>03 23 20 81 38</Téléphone>
      <Télécopie>03 23 20 81 38</Télécopie>
      <Email>mairie.bouffi@orange.fr</Email>
   </CoordonnéesNum>
   <Ouverture>
      <PlageJ début="lundi" fin="lundi">
         <PlageH début="17:00:00" fin="18:30:00"/>
      </PlageJ>
      <PlageJ début="jeudi" fin="jeudi">
         <PlageH début="17:00:00" fin="18:30:00"/>
      </PlageJ>
   </Ouverture>
</Organisme>