<?xml version="1.0" encoding="UTF-8"?>
<Organisme id="mairie-02003-01" codeInsee="02003" dateMiseAJour="2020-11-16"
           pivotLocal="mairie">
   <Nom>Mairie - Acy</Nom>
   <EditeurSource>La Direction de l'information légale et administrative (Premier ministre)</EditeurSource>
   <Adresse type="géopostale">
      <Ligne>3 bis place de la Mairie</Ligne>
      <CodePostal>02200</CodePostal>
      <NomCommune>Acy</NomCommune>
      <Localisation>
         <Latitude>49.3456001282</Latitude>
         <Longitude>3.41333007812</Longitude>
         <Précision>8</Précision>
      </Localisation>
      <Accessibilité type="DEM">sonnette, accueil dans une salle à côté</Accessibilité>
   </Adresse>
   <CoordonnéesNum>
      <Téléphone>03 23 72 42 42</Téléphone>
      <Email>mairie.acy@wanadoo.fr</Email>
   </CoordonnéesNum>
   <Ouverture>
      <PlageJ début="lundi" fin="mardi">
         <PlageH début="08:00:00" fin="12:00:00"/>
         <PlageH début="13:30:00" fin="17:30:00"/>
      </PlageJ>
      <PlageJ début="mercredi" fin="mercredi">
         <PlageH début="08:00:00" fin="12:00:00"/>
         <PlageH début="13:30:00" fin="16:30:00"/>
      </PlageJ>
      <PlageJ début="jeudi" fin="vendredi">
         <PlageH début="08:00:00" fin="12:00:00"/>
         <PlageH début="13:30:00" fin="17:30:00"/>
      </PlageJ>
   </Ouverture>
</Organisme>