<?xml version="1.0" encoding="UTF-8"?>
<Organisme id="crib-10387-03" codeInsee="10387" dateMiseAJour="2021-06-07"
           pivotLocal="crib">
   <Nom>Centre de ressources et d'information des bénévoles (CRIB) - Comité départemental olympique et sportif de l'Aube</Nom>
   <EditeurSource>La Direction de l'information légale et administrative (Premier ministre)</EditeurSource>
   <Adresse type="géopostale">
      <Ligne>Centre sportif de l'Aube</Ligne>
      <Ligne>5 rue Marie-Curie</Ligne>
      <CodePostal>10000</CodePostal>
      <NomCommune>Troyes</NomCommune>
      <Localisation>
         <Latitude>48.2702971</Latitude>
         <Longitude>4.0739499</Longitude>
         <Précision>8</Précision>
      </Localisation>
      <Accessibilité type="ACC"/>
   </Adresse>
   <CoordonnéesNum>
      <Téléphone>03 25 79 97 37</Téléphone>
      <Email>cdos.aube@wanadoo.fr</Email>
      <Url>http://aube.franceolympique.com</Url>
   </CoordonnéesNum>
   <Ouverture>
      <PlageJ début="lundi" fin="vendredi">
         <PlageH début="09:00:00" fin="12:00:00"/>
         <PlageH début="14:00:00" fin="18:00:00"/>
      </PlageJ>
   </Ouverture>
</Organisme>