<?xml version="1.0" encoding="UTF-8"?>
<Organisme id="mairie-80186-01" codeInsee="80186" dateMiseAJour="2020-11-16"
           pivotLocal="mairie">
   <Nom>Mairie - Chaulnes</Nom>
   <EditeurSource>La Direction de l'information légale et administrative (Premier ministre)</EditeurSource>
   <Adresse type="géopostale">
      <Ligne>7 rue des Lieutenants-Terpraut-et-Grenier</Ligne>
      <Ligne>BP 90023</Ligne>
      <CodePostal>80320</CodePostal>
      <NomCommune>Chaulnes</NomCommune>
      <Localisation>
         <Latitude>49.8148482</Latitude>
         <Longitude>2.8054448</Longitude>
         <Précision>8</Précision>
      </Localisation>
      <Accessibilité type="ACC"/>
   </Adresse>
   <CoordonnéesNum>
      <Téléphone>03 22 83 80 80</Téléphone>
      <Télécopie>03 22 83 80 89</Télécopie>
      <Email>mairie.chaulnes@wanadoo.fr</Email>
      <Url>http://www.mairiechaulnes.fr</Url>
   </CoordonnéesNum>
   <Ouverture>
      <PlageJ début="lundi" fin="mardi">
         <PlageH début="08:30:00" fin="12:00:00"/>
         <PlageH début="13:30:00" fin="17:00:00"/>
      </PlageJ>
      <PlageJ début="jeudi" fin="vendredi">
         <PlageH début="08:30:00" fin="12:00:00"/>
         <PlageH début="13:30:00" fin="17:00:00"/>
      </PlageJ>
   </Ouverture>
</Organisme>