<?xml version="1.0" encoding="UTF-8"?>
<Organisme id="pcb-76688-01" codeInsee="76688" dateMiseAJour="2021-11-29" pivotLocal="pcb">
   <Nom>Point conseil budget - Unités Territoriales d’Action Sociale (UTAS 76) - Thiergeville</Nom>
   <EditeurSource>La Direction de l'information légale et administrative (Premier ministre)</EditeurSource>
   <Adresse type="géopostale">
      <Ligne>CDS69</Ligne>
      <Ligne>Centre Médico-social</Ligne>
      <Ligne>Rue Guy de Maupassant</Ligne>
      <NomCommune>Thiergeville</NomCommune>
      <Localisation>
         <Latitude>49.742053</Latitude>
         <Longitude>0.511682</Longitude>
         <Précision>8</Précision>
      </Localisation>
   </Adresse>
   <CoordonnéesNum>
      <Téléphone>0800 740 976</Téléphone>
      <Email>Pcb_utas_esm@seinemaritime.fr</Email>
      <Url>https://www.seinemaritime.fr/mon-quotidien/insertion-emploi/points-conseil-budget.html</Url>
   </CoordonnéesNum>
   <Ouverture>
      <PlageJ début="lundi" fin="lundi">
         <PlageH début="08:45:00" fin="12:15:00"/>
      </PlageJ>
      <PlageJ début="jeudi" fin="jeudi">
         <PlageH début="08:45:00" fin="12:15:00"/>
      </PlageJ>
   </Ouverture>
</Organisme>