<?xml version="1.0" encoding="UTF-8"?>
<Organisme id="mairie-26039-01" codeInsee="26039" dateMiseAJour="2020-12-15"
           pivotLocal="mairie">
   <Nom>Mairie - Beauregard-Baret</Nom>
   <EditeurSource>La Direction de l'information légale et administrative (Premier ministre)</EditeurSource>
   <Adresse type="géopostale">
      <Ligne>Meymans</Ligne>
      <Ligne>1 place de la Mairie</Ligne>
      <CodePostal>26300</CodePostal>
      <NomCommune>Beauregard-Baret</NomCommune>
      <Localisation>
         <Latitude>45.0147018433</Latitude>
         <Longitude>5.15153980255</Longitude>
         <Précision>4</Précision>
      </Localisation>
      <Accessibilité type="ACC">plain-pied</Accessibilité>
   </Adresse>
   <CoordonnéesNum>
      <Téléphone>04 75 48 80 88</Téléphone>
      <Télécopie>04 75 48 89 83</Télécopie>
      <Email>mairie.beauregard.baret@wanadoo.fr</Email>
   </CoordonnéesNum>
   <Ouverture>
      <PlageJ début="mardi" fin="mardi">
         <PlageH début="13:00:00" fin="19:00:00"/>
      </PlageJ>
      <PlageJ début="mercredi" fin="mercredi">
         <PlageH début="08:00:00" fin="13:00:00"/>
      </PlageJ>
      <PlageJ début="jeudi" fin="jeudi">
         <PlageH début="13:00:00" fin="16:30:00"/>
      </PlageJ>
      <PlageJ début="vendredi" fin="vendredi">
         <PlageH début="08:00:00" fin="12:30:00"/>
      </PlageJ>
   </Ouverture>
</Organisme>