<?xml version="1.0" encoding="UTF-8"?>
<Organisme id="mairie-03221-01" codeInsee="03221" dateMiseAJour="2021-06-07"
           pivotLocal="mairie">
   <Nom>Mairie - Saint-Bonnet-Tronçais</Nom>
   <EditeurSource>La Direction de l'information légale et administrative (Premier ministre)</EditeurSource>
   <Adresse type="géopostale">
      <Ligne>6 rue de la Mairie</Ligne>
      <CodePostal>03360</CodePostal>
      <NomCommune>Saint-Bonnet-Tronçais</NomCommune>
      <Localisation>
         <Latitude>46.660019</Latitude>
         <Longitude>2.693311</Longitude>
         <Précision>8</Précision>
      </Localisation>
      <Accessibilité type="ACC"/>
   </Adresse>
   <CoordonnéesNum>
      <Téléphone>04 70 06 10 22</Téléphone>
      <Télécopie>04 70 06 11 20</Télécopie>
      <Email>mairie.saintbonnettroncais@wanadoo.fr</Email>
      <Url>http://www.saintbonnettroncais.fr</Url>
   </CoordonnéesNum>
   <Ouverture>
      <PlageJ début="samedi" fin="samedi">
         <PlageH début="09:00:00" fin="11:30:00"/>
      </PlageJ>
      <PlageJ début="lundi" fin="vendredi">
         <PlageH début="09:00:00" fin="12:00:00"/>
         <PlageH début="14:00:00" fin="17:30:00"/>
      </PlageJ>
   </Ouverture>
</Organisme>