<?xml version="1.0" encoding="UTF-8"?>
<Organisme id="mairie-03063-01" codeInsee="03063" dateMiseAJour="2021-06-07"
           pivotLocal="mairie">
   <Nom>Mairie - Chassenard</Nom>
   <EditeurSource>La Direction de l'information légale et administrative (Premier ministre)</EditeurSource>
   <Adresse type="géopostale">
      <Ligne>1 rue du Centre</Ligne>
      <CodePostal>03510</CodePostal>
      <NomCommune>Chassenard</NomCommune>
      <Localisation>
         <Latitude>46.438111</Latitude>
         <Longitude>3.979673</Longitude>
         <Précision>8</Précision>
      </Localisation>
      <Accessibilité type="ACC"/>
   </Adresse>
   <CoordonnéesNum>
      <Téléphone>03 85 53 08 79</Téléphone>
      <Télécopie>03 85 53 19 92</Télécopie>
      <Email>chassenard.mairie@orange.fr</Email>
      <Url>http://www.chassenard.com</Url>
   </CoordonnéesNum>
   <Ouverture>
      <PlageJ début="lundi" fin="mardi">
         <PlageH début="09:00:00" fin="12:00:00"/>
         <PlageH début="13:00:00" fin="17:00:00"/>
      </PlageJ>
      <PlageJ début="jeudi" fin="vendredi">
         <PlageH début="09:00:00" fin="12:00:00"/>
         <PlageH début="13:00:00" fin="17:00:00"/>
      </PlageJ>
   </Ouverture>
</Organisme>