<?xml version="1.0" encoding="UTF-8"?>
<Organisme id="pif-66021-01" codeInsee="66021" dateMiseAJour="2021-09-20" pivotLocal="pif">
   <Nom>Point info famille - Bompas</Nom>
   <EditeurSource>La Direction de l'information légale et administrative (Premier ministre)</EditeurSource>
   <Adresse type="géopostale">
      <Ligne>Centre social de Bompas</Ligne>
      <Ligne>Place Vidal</Ligne>
      <CodePostal>66430</CodePostal>
      <NomCommune>Bompas</NomCommune>
      <Localisation>
         <Latitude>42.7319145203</Latitude>
         <Longitude>2.93327093124</Longitude>
         <Précision>4</Précision>
      </Localisation>
   </Adresse>
   <CoordonnéesNum>
      <Téléphone>04 68 34 76 38</Téléphone>
      <Télécopie>04 68 34 76 40</Télécopie>
      <Email>accueil.solidarite.bompas@wanadoo.fr</Email>
      <Url>http://www.point-infofamille.fr</Url>
   </CoordonnéesNum>
</Organisme>