<?xml version="1.0" encoding="UTF-8"?>
<Organisme id="mairie-28396-01" codeInsee="28396" dateMiseAJour="2021-03-08"
           pivotLocal="mairie">
   <Nom>Mairie - Trizay-lès-Bonneval</Nom>
   <EditeurSource>La Direction de l'information légale et administrative (Premier ministre)</EditeurSource>
   <Adresse type="géopostale">
      <Ligne>3 rue de la Salva</Ligne>
      <CodePostal>28800</CodePostal>
      <NomCommune>Trizay-lès-Bonneval</NomCommune>
      <Localisation>
         <Latitude>48.2006454468</Latitude>
         <Longitude>1.33315598965</Longitude>
         <Précision>4</Précision>
      </Localisation>
      <Accessibilité type="DEM">en passant par la salle communale</Accessibilité>
   </Adresse>
   <CoordonnéesNum>
      <Téléphone>02 37 47 31 59</Téléphone>
      <Email>mairie.trizaylesbonneval@gmail.com</Email>
   </CoordonnéesNum>
   <Ouverture>
      <PlageJ début="mardi" fin="mardi">
         <PlageH début="10:00:00" fin="12:00:00"/>
         <PlageH début="14:00:00" fin="15:00:00"/>
      </PlageJ>
      <PlageJ début="vendredi" fin="vendredi">
         <PlageH début="14:00:00" fin="19:00:00"/>
      </PlageJ>
   </Ouverture>
</Organisme>