<?xml version="1.0" encoding="UTF-8"?>
<Organisme id="clic-75110-01" codeInsee="75110" dateMiseAJour="2018-04-12"
           pivotLocal="clic">
   <Nom>Point d'information local dédié aux personnes âgées - Paris 9e - 10e - 19e arrondissement</Nom>
   <EditeurSource>La Direction de l'information légale et administrative (Premier ministre)</EditeurSource>
   <Adresse type="géopostale">
      <Ligne>Maison des aînés et des aidants</Ligne>
      <Ligne>126 quai de Jemmapes</Ligne>
      <CodePostal>75010</CodePostal>
      <NomCommune>Paris</NomCommune>
      <Localisation>
         <Latitude>48.875631</Latitude>
         <Longitude>2.364478</Longitude>
         <Précision>8</Précision>
      </Localisation>
      <Accessibilité type="ACC"/>
   </Adresse>
   <CoordonnéesNum>
      <Téléphone>01 40 40 27 80</Téléphone>
      <Télécopie>01 40 40 27 92</Télécopie>
      <Email>casvp-m2a@paris.fr</Email>
   </CoordonnéesNum>
   <Ouverture>
      <PlageJ début="lundi" fin="vendredi">
         <PlageH début="09:00:00" fin="17:30:00"/>
      </PlageJ>
   </Ouverture>
</Organisme>