<?xml version="1.0" encoding="UTF-8"?>
<Organisme id="ordre_avocats-17300-01" codeInsee="17300" dateMiseAJour="2019-03-05"
           pivotLocal="ordre_avocats">
   <Nom>Ordre des avocats - Barreau de La Rochelle-Rochefort</Nom>
   <EditeurSource>La Direction de l'information légale et administrative (Premier ministre)</EditeurSource>
   <Adresse type="géopostale">
      <Ligne>32-34 rue Gargoulleau</Ligne>
      <Ligne>Maison des Avocats</Ligne>
      <CodePostal>17000</CodePostal>
      <NomCommune>La Rochelle</NomCommune>
      <Localisation>
         <Latitude>46.162146</Latitude>
         <Longitude>-1.152076</Longitude>
         <Précision>8</Précision>
      </Localisation>
   </Adresse>
   <CoordonnéesNum>
      <Téléphone>05 46 41 47 06</Téléphone>
      <Télécopie>05 46 41 45 98</Télécopie>
      <Email>ordre@avocats-larochelle.com</Email>
      <Url>https://www.avocats-larochelle.com</Url>
   </CoordonnéesNum>
   <Ouverture>
      <PlageJ début="lundi" fin="jeudi">
         <PlageH début="10:00:00" fin="12:00:00"/>
         <PlageH début="14:30:00" fin="17:00:00"/>
      </PlageJ>
      <PlageJ début="vendredi" fin="vendredi">
         <PlageH début="10:00:00" fin="12:00:00"/>
         <PlageH début="14:30:00" fin="16:00:00"/>
      </PlageJ>
   </Ouverture>
</Organisme>