<?xml version="1.0" encoding="UTF-8"?>
<Organisme id="mairie-55043-01" codeInsee="55043" dateMiseAJour="2021-05-10"
           pivotLocal="mairie">
   <Nom>Mairie - Belleville-sur-Meuse</Nom>
   <EditeurSource>La Direction de l'information légale et administrative (Premier ministre)</EditeurSource>
   <Adresse type="géopostale">
      <Ligne>21 rue du Général-de-Gaulle</Ligne>
      <CodePostal>55430</CodePostal>
      <NomCommune>Belleville-sur-Meuse</NomCommune>
      <Localisation>
         <Latitude>49.1743011475</Latitude>
         <Longitude>5.38094997406</Longitude>
         <Précision>8</Précision>
      </Localisation>
      <Accessibilité type="ACC">rampe</Accessibilité>
   </Adresse>
   <CoordonnéesNum>
      <Téléphone>03 29 84 31 81</Téléphone>
      <Télécopie>03 29 83 75 81</Télécopie>
      <Email>mairie-belleville-meuse@wanadoo.fr</Email>
      <Url>http://www.belleville-sur-meuse.com</Url>
   </CoordonnéesNum>
   <Ouverture>
      <PlageJ début="mardi" fin="mardi">
         <PlageH début="08:30:00" fin="12:00:00"/>
         <PlageH début="16:00:00" fin="18:00:00"/>
      </PlageJ>
      <PlageJ début="lundi" fin="lundi">
         <PlageH début="08:30:00" fin="12:00:00"/>
      </PlageJ>
      <PlageJ début="mercredi" fin="mercredi">
         <PlageH début="10:00:00" fin="12:00:00"/>
         <PlageH début="13:30:00" fin="17:00:00"/>
      </PlageJ>
      <PlageJ début="jeudi" fin="vendredi">
         <PlageH début="08:30:00" fin="12:00:00"/>
      </PlageJ>
   </Ouverture>
</Organisme>